flottplot/__init__.py
flottplot/__main__.py
flottplot/assets.py
flottplot/convert.py
flottplot/ipython.py
flottplot/assets/flottplot-min.js
flottplot/assets/flottplot-scan-min.js
flottplot/assets/flottplot.css
flottplot-2.2.0.dist-info/METADATA
flottplot-2.2.0.dist-info/WHEEL
flottplot-2.2.0.dist-info/top_level.txt
flottplot-2.2.0.dist-info/RECORD
