Metadata-Version: 2.1
Name: flottplot
Version: 2.2.0
Summary: Quickly arrange and navigate collections of images in the browser.
Home-page: https://github.com/chpolste/flottplot
Author: Christopher Polster
License: UNKNOWN
Platform: UNKNOWN
